semgrep-1.150.0.data/purelib/semdep/__init__.py
semgrep-1.150.0.data/purelib/semdep/golang_version.py
semgrep-1.150.0.data/purelib/semdep/maven_version.py
semgrep-1.150.0.data/purelib/semdep/package_restrictions.py
semgrep-1.150.0.data/purelib/semdep/semver_specifier.py
semgrep-1.150.0.data/purelib/semdep/subproject_matchers.py
semgrep-1.150.0.data/purelib/semdep/external/__init__.py
semgrep-1.150.0.data/purelib/semdep/external/packaging/__about__.py
semgrep-1.150.0.data/purelib/semdep/external/packaging/__init__.py
semgrep-1.150.0.data/purelib/semdep/external/packaging/_manylinux.py
semgrep-1.150.0.data/purelib/semdep/external/packaging/_musllinux.py
semgrep-1.150.0.data/purelib/semdep/external/packaging/_structures.py
semgrep-1.150.0.data/purelib/semdep/external/packaging/py.typed
semgrep-1.150.0.data/purelib/semdep/external/packaging/specifiers.py
semgrep-1.150.0.data/purelib/semdep/external/packaging/tags.py
semgrep-1.150.0.data/purelib/semdep/external/packaging/utils.py
semgrep-1.150.0.data/purelib/semdep/external/packaging/version.py
semgrep-1.150.0.data/purelib/semdep/external/parsy/__init__.py
semgrep-1.150.0.data/purelib/semdep/external/parsy/__init__.pyi
semgrep-1.150.0.data/purelib/semdep/external/parsy/version.py
semgrep-1.150.0.data/purelib/semdep/matchers/__init__.py
semgrep-1.150.0.data/purelib/semdep/matchers/base.py
semgrep-1.150.0.data/purelib/semdep/matchers/gradle.py
semgrep-1.150.0.data/purelib/semdep/matchers/pip_requirements.py
semgrep-1.150.0.data/purelib/semdep/parsers/__init__.py
semgrep-1.150.0.data/purelib/semdep/parsers/cargo.py
semgrep-1.150.0.data/purelib/semdep/parsers/composer.py
semgrep-1.150.0.data/purelib/semdep/parsers/gem.py
semgrep-1.150.0.data/purelib/semdep/parsers/go_mod.py
semgrep-1.150.0.data/purelib/semdep/parsers/gradle.py
semgrep-1.150.0.data/purelib/semdep/parsers/mix.py
semgrep-1.150.0.data/purelib/semdep/parsers/package_lock.py
semgrep-1.150.0.data/purelib/semdep/parsers/packages_lock_c_sharp.py
semgrep-1.150.0.dist-info/licenses/LICENSE
semgrep-1.150.0.dist-info/METADATA
semgrep-1.150.0.dist-info/WHEEL
semgrep-1.150.0.dist-info/entry_points.txt
semgrep-1.150.0.dist-info/top_level.txt
semgrep-1.150.0.dist-info/RECORD
